{
  "chunkId" : 81,
  "customers" : [ {
    "id" : 811,
    "name" : "Dallan",
    "email" : "mdallanmi@mapy.cz"
  }, {
    "id" : 812,
    "name" : "Parkin",
    "email" : "tparkinmj@paginegialle.it"
  }, {
    "id" : 813,
    "name" : "Vegas",
    "email" : "evegasmk@baidu.com"
  }, {
    "id" : 814,
    "name" : "Sapsforde",
    "email" : "tsapsfordeml@va.gov"
  }, {
    "id" : 815,
    "name" : "Shalliker",
    "email" : "gshallikermm@sourceforge.net"
  }, {
    "id" : 816,
    "name" : "Dwight",
    "email" : "vdwightmn@360.cn"
  }, {
    "id" : 817,
    "name" : "Burgoine",
    "email" : "bburgoinemo@odnoklassniki.ru"
  }, {
    "id" : 818,
    "name" : "Carmont",
    "email" : "gcarmontmp@webeden.co.uk"
  }, {
    "id" : 819,
    "name" : "Charte",
    "email" : "fchartemq@imageshack.us"
  }, {
    "id" : 820,
    "name" : "Blowen",
    "email" : "sblowenmr@dyndns.org"
  } ]
}