{
  "chunkId" : 3,
  "customers" : [ {
    "id" : 31,
    "name" : "Breen",
    "email" : "mbreenu@gravatar.com"
  }, {
    "id" : 32,
    "name" : "Doret",
    "email" : "mdoretv@flavors.me"
  }, {
    "id" : 33,
    "name" : "Garland",
    "email" : "ggarlandw@webeden.co.uk"
  }, {
    "id" : 34,
    "name" : "Armytage",
    "email" : "aarmytagex@cocolog-nifty.com"
  }, {
    "id" : 35,
    "name" : "Hamlen",
    "email" : "ihamleny@sakura.ne.jp"
  }, {
    "id" : 36,
    "name" : "Kenworth",
    "email" : "mkenworthz@gmpg.org"
  }, {
    "id" : 37,
    "name" : "O'Keefe",
    "email" : "jokeefe10@artisteer.com"
  }, {
    "id" : 38,
    "name" : "Golby",
    "email" : "dgolby11@privacy.gov.au"
  }, {
    "id" : 39,
    "name" : "Benez",
    "email" : "bbenez12@ustream.tv"
  }, {
    "id" : 40,
    "name" : "Mahedy",
    "email" : "gmahedy13@sbwire.com"
  } ]
}